{
  "login": 32081,
  "utc": "2026-07-22T10:52:52Z",
  "duration_s": 1200,
  "interval_s": 5,
  "stats": {
    "USDJPY.b": {
      "min": 3,
      "max": 9,
      "mean": 4.06,
      "median": 3.0,
      "mode": 3,
      "count": 240
    },
    "EURJPY.b": {
      "min": 5,
      "max": 9,
      "mean": 6.93,
      "median": 7.0,
      "mode": 5,
      "count": 240
    },
    "USDCAD.b": {
      "min": 4,
      "max": 7,
      "mean": 5.92,
      "median": 6.0,
      "mode": 7,
      "count": 240
    },
    "NZDUSD.b": {
      "min": 4,
      "max": 7,
      "mean": 5.77,
      "median": 6.0,
      "mode": 5,
      "count": 240
    }
  }
}
